MANIFEST.in
README.rst
setup.py
src/model_old_schema/J_Medline.txt
src/model_old_schema/__init__.py
src/model_old_schema/feature.py
src/model_old_schema/model.py
src/model_old_schema/pubmed.py
src/model_old_schema/reference.py
src/model_old_schema/sequence.py
src/model_old_schema/taxonomy.py
src/model_old_schema/test_model.py
src/queries/__init__.py
src/queries/associate.py
src/queries/misc.py
src/queries/move_ref.py
src/queries/test_queries.py
src/webapp/__init__.py
src/webapp/config.py
src/webapp/example_config.py
src/webapp/forms.py
src/webapp/litreview_log
src/webapp/litreview_logger.py
src/webapp/login_handler.py
src/webapp/main.py
src/webapp/router.py
src/webapp/users.py
src/webapp/logs/run_login.log2
src/webapp/static/css/bootstrap-responsive.css
src/webapp/static/css/bootstrap-responsive.min.css
src/webapp/static/css/bootstrap.css
src/webapp/static/css/bootstrap.min.css
src/webapp/static/ico/apple-touch-icon-114-precomposed.png
src/webapp/static/ico/apple-touch-icon-57-precomposed.png
src/webapp/static/ico/apple-touch-icon-72-precomposed.png
src/webapp/static/ico/favicon.ico
src/webapp/static/img/full_text.gif
src/webapp/static/img/glyphicons-halflings-white.png
src/webapp/static/img/glyphicons-halflings.png
src/webapp/static/img/minus.gif
src/webapp/static/img/plus.gif
src/webapp/static/img/pubmedrefsml.gif
src/webapp/static/js/bootstrap.js
src/webapp/static/js/bootstrap.min.js
src/webapp/static/js/jquery-1.7.2.min.js
src/webapp/static/js/local.js
src/webapp/templates/index.html
src/webapp/templates/layout.html
src/webapp/templates/literature_review.html
src/webapp/templates/login.html
src/webapp/templates/reauth.html
src/webapp/templates/error_pages/404.html
src/webapp/templates/error_pages/500.html
src/webapp/templates/layout/footer.html
src/webapp/templates/layout/header.html
src/webapp/templates/layout/nav.html