Metadata-Version: 1.0
Name: LitReview
Version: 0.71
Summary: Literature curation tool.
Home-page: http://cherry-vm13.stanford.edu
Author: Kelley Paskov
Author-email: kpaskov@stanford.edu
License: MIT
Platform: UNKNOWN
